<?xml version="1.0" encoding="utf-8" ?><dwsync><file name="bg-slide1.png" server="roycalvillo.com/www/test/roth_1/" local="3744050504" remote="3752622300" Dst="-1" /><file name="bg-slide2.png" server="roycalvillo.com/www/test/roth_1/" local="3744050504" remote="3752622300" Dst="-1" /><file name="bg-slide3.png" server="roycalvillo.com/www/test/roth_1/" local="3744050504" remote="3752622300" Dst="-1" /><file name="bg-mono.jpg" server="roycalvillo.com/www/test/roth_1/" local="3744120877" remote="3752622300" Dst="-1" /><file name="bg-slide1.png" server="roycalvillo.com/www/test/roth_0/" local="3744050504" remote="3752679120" Dst="-1" /><file name="bg-slide2.png" server="roycalvillo.com/www/test/roth_0/" local="3744050504" remote="3752679120" Dst="-1" /><file name="bg-slide3.png" server="roycalvillo.com/www/test/roth_0/" local="3744050504" remote="3752679120" Dst="-1" /><file name="bg-mono.jpg" server="roycalvillo.com/www/test/roth_0/" local="3744120877" remote="3752679120" Dst="-1" /></dwsync>